{
"meta":{"test_sets":[],"test_metrics":[],"learn_metrics":[{"best_value":"Min","name":"RMSE"}],"launch_mode":"Train","parameters":"","iteration_count":100,"learn_sets":["learn"],"name":"experiment"},
"iterations":[
{"learn":[14.005006],"iteration":0,"passed_time":0.001619108497,"remaining_time":0.1602917412},
{"learn":[13.14441192],"iteration":1,"passed_time":0.00290112266,"remaining_time":0.1421550103},
{"learn":[12.34258257],"iteration":2,"passed_time":0.004076872493,"remaining_time":0.1318188773},
{"learn":[11.64527793],"iteration":3,"passed_time":0.006114305523,"remaining_time":0.1467433325},
{"learn":[11.02766183],"iteration":4,"passed_time":0.007406861092,"remaining_time":0.1407303608},
{"learn":[10.43485794],"iteration":5,"passed_time":0.008719627332,"remaining_time":0.1366074949},
{"learn":[9.890641275],"iteration":6,"passed_time":0.01027350375,"remaining_time":0.1364908355},
{"learn":[9.492161212],"iteration":7,"passed_time":0.01151225675,"remaining_time":0.1323909526},
{"learn":[9.105082953],"iteration":8,"passed_time":0.01278598121,"remaining_time":0.1292804767},
{"learn":[8.674157135],"iteration":9,"passed_time":0.014019081,"remaining_time":0.126171729},
{"learn":[8.341743544],"iteration":10,"passed_time":0.01520076442,"remaining_time":0.1229880031},
{"learn":[8.049372916],"iteration":11,"passed_time":0.01640329176,"remaining_time":0.1202908063},
{"learn":[7.757318612],"iteration":12,"passed_time":0.01774119517,"remaining_time":0.1187295369},
{"learn":[7.522206899],"iteration":13,"passed_time":0.02054715521,"remaining_time":0.1262182392},
{"learn":[7.297756655],"iteration":14,"passed_time":0.02213763295,"remaining_time":0.1254465867},
{"learn":[7.088359431],"iteration":15,"passed_time":0.02339531143,"remaining_time":0.122825385},
{"learn":[6.882113791],"iteration":16,"passed_time":0.02461419249,"remaining_time":0.1201751751},
{"learn":[6.704728832],"iteration":17,"passed_time":0.0259265621,"remaining_time":0.118109894},
{"learn":[6.563881962],"iteration":18,"passed_time":0.02730349087,"remaining_time":0.1163990926},
{"learn":[6.418790279],"iteration":19,"passed_time":0.02857935808,"remaining_time":0.1143174323},
{"learn":[6.315756953],"iteration":20,"passed_time":0.02977115299,"remaining_time":0.1119962422},
{"learn":[6.210157751],"iteration":21,"passed_time":0.03103809588,"remaining_time":0.1100441581},
{"learn":[6.115058449],"iteration":22,"passed_time":0.03223376871,"remaining_time":0.1079130518},
{"learn":[6.014819884],"iteration":23,"passed_time":0.03340424921,"remaining_time":0.1057801225},
{"learn":[5.93117229],"iteration":24,"passed_time":0.03675087647,"remaining_time":0.1102526294},
{"learn":[5.844857622],"iteration":25,"passed_time":0.03798694146,"remaining_time":0.1081166795},
{"learn":[5.771145213],"iteration":26,"passed_time":0.0392216629,"remaining_time":0.1060437553},
{"learn":[5.704018229],"iteration":27,"passed_time":0.04041100368,"remaining_time":0.1039140095},
{"learn":[5.665806474],"iteration":28,"passed_time":0.04169249903,"remaining_time":0.102074739},
{"learn":[5.616500369],"iteration":29,"passed_time":0.04297991018,"remaining_time":0.1002864571},
{"learn":[5.558023666],"iteration":30,"passed_time":0.04440176142,"remaining_time":0.09882972704},
{"learn":[5.510080976],"iteration":31,"passed_time":0.04572308406,"remaining_time":0.09716155364},
{"learn":[5.468747792],"iteration":32,"passed_time":0.04689920364,"remaining_time":0.09521959526},
{"learn":[5.429275534],"iteration":33,"passed_time":0.04808424752,"remaining_time":0.0933400099},
{"learn":[5.402117324],"iteration":34,"passed_time":0.05214991527,"remaining_time":0.09684984264},
{"learn":[5.367635151],"iteration":35,"passed_time":0.05356208813,"remaining_time":0.09522149001},
{"learn":[5.345181232],"iteration":36,"passed_time":0.05477692123,"remaining_time":0.09326881182},
{"learn":[5.319151269],"iteration":37,"passed_time":0.05598128586,"remaining_time":0.09133788746},
{"learn":[5.296134146],"iteration":38,"passed_time":0.057215602,"remaining_time":0.0894910698},
{"learn":[5.269629003],"iteration":39,"passed_time":0.05840879563,"remaining_time":0.08761319344},
{"learn":[5.251147059],"iteration":40,"passed_time":0.05968359785,"remaining_time":0.085886153},
{"learn":[5.248003302],"iteration":41,"passed_time":0.06016495609,"remaining_time":0.08308493936},
{"learn":[5.232376509],"iteration":42,"passed_time":0.06152101951,"remaining_time":0.08155111889},
{"learn":[5.213524255],"iteration":43,"passed_time":0.06272840405,"remaining_time":0.07983615061},
{"learn":[5.189691584],"iteration":44,"passed_time":0.06561044349,"remaining_time":0.08019054204},
{"learn":[5.166052198],"iteration":45,"passed_time":0.06724030904,"remaining_time":0.07893427583},
{"learn":[5.140406659],"iteration":46,"passed_time":0.06849113938,"remaining_time":0.07723468909},
{"learn":[5.118929684],"iteration":47,"passed_time":0.07102872894,"remaining_time":0.07694778968},
{"learn":[5.108792602],"iteration":48,"passed_time":0.07306393898,"remaining_time":0.07604614057},
{"learn":[5.098141225],"iteration":49,"passed_time":0.07468561102,"remaining_time":0.07468561102},
{"learn":[5.085926393],"iteration":50,"passed_time":0.07593324138,"remaining_time":0.07295546721},
{"learn":[5.067816804],"iteration":51,"passed_time":0.07721500388,"remaining_time":0.0712753882},
{"learn":[5.049834901],"iteration":52,"passed_time":0.07978928731,"remaining_time":0.0707565378},
{"learn":[5.03838627],"iteration":53,"passed_time":0.08636931768,"remaining_time":0.07357386321},
{"learn":[5.033534248],"iteration":54,"passed_time":0.08818685282,"remaining_time":0.07215287958},
{"learn":[5.023726885],"iteration":55,"passed_time":0.09016018715,"remaining_time":0.07084014705},
{"learn":[5.01290392],"iteration":56,"passed_time":0.09137635513,"remaining_time":0.06893303983},
{"learn":[5.005569127],"iteration":57,"passed_time":0.0925976379,"remaining_time":0.06705346192},
{"learn":[4.989969032],"iteration":58,"passed_time":0.09535408223,"remaining_time":0.0662630063},
{"learn":[4.976762446],"iteration":59,"passed_time":0.09720217204,"remaining_time":0.06480144803},
{"learn":[4.967222715],"iteration":60,"passed_time":0.09843429939,"remaining_time":0.06293340453},
{"learn":[4.954407599],"iteration":61,"passed_time":0.09963710939,"remaining_time":0.06106790576},
{"learn":[4.942125056],"iteration":62,"passed_time":0.1007949422,"remaining_time":0.05919702955},
{"learn":[4.930230716],"iteration":63,"passed_time":0.1020407116,"remaining_time":0.05739790025},
{"learn":[4.921695642],"iteration":64,"passed_time":0.1034167591,"remaining_time":0.05568594719},
{"learn":[4.906405625],"iteration":65,"passed_time":0.1048630709,"remaining_time":0.05402036987},
{"learn":[4.894330248],"iteration":66,"passed_time":0.1060892414,"remaining_time":0.05225290996},
{"learn":[4.88211557],"iteration":67,"passed_time":0.1073724095,"remaining_time":0.0505281927},
{"learn":[4.877946398],"iteration":68,"passed_time":0.1095400304,"remaining_time":0.04921363684},
{"learn":[4.863182126],"iteration":69,"passed_time":0.1115958008,"remaining_time":0.04782677177},
{"learn":[4.84646533],"iteration":70,"passed_time":0.1130918431,"remaining_time":0.04619244295},
{"learn":[4.838014752],"iteration":71,"passed_time":0.1143746136,"remaining_time":0.04447901639},
{"learn":[4.82981137],"iteration":72,"passed_time":0.115573811,"remaining_time":0.04274647804},
{"learn":[4.817094767],"iteration":73,"passed_time":0.1168096252,"remaining_time":0.04104121968},
{"learn":[4.808314151],"iteration":74,"passed_time":0.1180310863,"remaining_time":0.03934369542},
{"learn":[4.796235023],"iteration":75,"passed_time":0.1192035253,"remaining_time":0.03764321853},
{"learn":[4.784434534],"iteration":76,"passed_time":0.1204857305,"remaining_time":0.03598924418},
{"learn":[4.774402487],"iteration":77,"passed_time":0.1225537611,"remaining_time":0.03456644543},
{"learn":[4.76731896],"iteration":78,"passed_time":0.1270122059,"remaining_time":0.03376273827},
{"learn":[4.75934113],"iteration":79,"passed_time":0.1285447332,"remaining_time":0.03213618331},
{"learn":[4.754106378],"iteration":80,"passed_time":0.1302826794,"remaining_time":0.03056013468},
{"learn":[4.744002932],"iteration":81,"passed_time":0.1315541143,"remaining_time":0.02887773242},
{"learn":[4.731700554],"iteration":82,"passed_time":0.1327435572,"remaining_time":0.02718843944},
{"learn":[4.723284153],"iteration":83,"passed_time":0.1339026383,"remaining_time":0.02550526444},
{"learn":[4.712232782],"iteration":84,"passed_time":0.1350976154,"remaining_time":0.02384075567},
{"learn":[4.703046867],"iteration":85,"passed_time":0.1364189467,"remaining_time":0.02220773552},
{"learn":[4.698601855],"iteration":86,"passed_time":0.1377222183,"remaining_time":0.02057918205},
{"learn":[4.692429407],"iteration":87,"passed_time":0.140910843,"remaining_time":0.01921511496},
{"learn":[4.675027364],"iteration":88,"passed_time":0.1423858622,"remaining_time":0.01759825263},
{"learn":[4.662368584],"iteration":89,"passed_time":0.1436585837,"remaining_time":0.01596206486},
{"learn":[4.646206172],"iteration":90,"passed_time":0.1448956184,"remaining_time":0.01433033589},
{"learn":[4.641245848],"iteration":91,"passed_time":0.1461153962,"remaining_time":0.01270568663},
{"learn":[4.633900435],"iteration":92,"passed_time":0.1475711307,"remaining_time":0.01110750446},
{"learn":[4.624738236],"iteration":93,"passed_time":0.1487810637,"remaining_time":0.009496663643},
{"learn":[4.612798287],"iteration":94,"passed_time":0.149956783,"remaining_time":0.007892462264},
{"learn":[4.605222001],"iteration":95,"passed_time":0.1512733292,"remaining_time":0.006303055382},
{"learn":[4.601725912],"iteration":96,"passed_time":0.1524544897,"remaining_time":0.004715087309},
{"learn":[4.59722371],"iteration":97,"passed_time":0.1547319857,"remaining_time":0.003157795626},
{"learn":[4.580235665],"iteration":98,"passed_time":0.1568559442,"remaining_time":0.001584403477},
{"learn":[4.57591791],"iteration":99,"passed_time":0.158047839,"remaining_time":0}
]}